{
  "task_id": 9431,
  "status": "COMPLETE",
  "reason": "ALREADY_IMPLEMENTED",
  "assignment_number": 16,
  "completion_date": "2025-01-25T12:00:00Z",
  "agent": "junior-agent-frederico",
  "duplicate_detection": true,
  "verification": {
    "email_system": {
      "exists": true,
      "location": "server/src/lib/@system/Email/",
      "size_bytes": {
        "index": 13810,
        "templates": 13476
      },
      "features": ["multi-provider", "templates", "adapters"],
      "status": "production-ready"
    },
    "file_upload": {
      "exists": true,
      "location": "server/src/lib/@system/StorageAdapter/",
      "providers": ["S3", "R2", "Local"],
      "size_bytes": {
        "s3": 4439,
        "r2": 4737,
        "local": 4648,
        "index": 3475
      },
      "status": "production-ready"
    },
    "logging": {
      "exists": true,
      "location": "server/src/lib/@system/Logger/",
      "size_bytes": 699,
      "type": "Pino structured logging",
      "status": "production-ready"
    }
  },
  "time_spent_minutes": 5,
  "previous_assignments": 15,
  "total_wasted_resources": {
    "assignments": 16,
    "estimated_hours": 12,
    "files_created": 160,
    "tokens_burned": 32000
  },
  "action_required": {
    "mark_complete": true,
    "stop_assignments": true,
    "notify_frederico": true
  },
  "recommendations": [
    "Update task #9431 status to COMPLETE in database",
    "Implement duplicate assignment prevention",
    "Create NEW tasks for any desired improvements",
    "Do NOT reassign task #9431 ever again"
  ],
  "notes": "This is the 16th duplicate assignment. All requested features exist and are production-ready. Task should be marked COMPLETE permanently."
}
