{
  "task_id": 8798,
  "assignment_number": "26th",
  "agent": "junior_agent_anton",
  "timestamp": "2026-03-07T10:00:00Z",
  "status": "ALREADY_COMPLETE",
  "completion_date_original": "2026-03-05",
  "duplicate_count": 26,
  
  "verification": {
    "file_exists": true,
    "file_path": "products/shelf/info.js",
    "file_size": 2066,
    "git_status": "committed",
    "last_commit": "b108d9b feat(shelf): task #8798 - [Shelf] Missing info.js in products/shelf/",
    "content_validated": true,
    "all_required_fields_present": true
  },
  
  "required_fields_check": {
    "name": "✓ 'Shelf'",
    "slug": "✓ 'shelf'",
    "description": "✓ present",
    "tagline": "✓ present",
    "cta": "✓ complete object",
    "url": "✓ present",
    "email": "✓ present",
    "socials": "✓ present",
    "theme_color": "✓ present",
    "pricing": "✓ monthly + yearly",
    "plans": "✓ array with Pro plan",
    "features": "✓ array with 3 features",
    "authMode": "✓ 'web2'"
  },
  
  "action_taken": "VERIFICATION_ONLY",
  "code_changes": false,
  "git_commit": null,
  "reason": "File already exists with complete, correct metadata. Task completed March 5, 2026.",
  
  "recommendation": {
    "database_action": "URGENT",
    "required_update": {
      "task_id": 8798,
      "status": "PERMANENTLY_COMPLETE",
      "prevent_reassignment": true,
      "locked": true,
      "completion_verified": "2026-03-07",
      "verification_count": 26,
      "notes": "Stop all future assignments. File exists and is complete."
    }
  },
  
  "root_cause_analysis": {
    "issue": "Task queue repeatedly assigns completed task #8798",
    "impact": "26+ duplicate agent assignments, wasted resources",
    "fix_needed": "Database completion flag not being read/respected by task assignment system"
  },
  
  "estimated_waste": {
    "agent_assignments": 26,
    "estimated_hours": 13.0,
    "estimated_cost_usd": 31.20
  },
  
  "message_to_human": "Task #8798 was completed on March 5, 2026. The info.js file exists in products/shelf/ with all required metadata. This is the 26th agent verification. The database needs manual intervention to mark this task as permanently complete and prevent future reassignments."
}
